{
    "projects": 
        {
            "title": "Bookswap System",
            "desc": "During this project I used React to build an application based on a supplied design and utalising an existing API. The application implemented features such as pagination, search and filters, all with a crisp responsive front-end based on a provided design, it allowed me to practice working with a CSS framework while building a modern React UI that consumes an existing API.",
            "img": "hhttps://iili.io/3oEkZbt.md.jpg",
            "alt": "Bookswap System",
            "url": "https://2025-htmelephant-bookswap.dev.io-academy.uk/",
            "github": "https://github.com/jasonb2222",
            "skillset": ["CSS", "JS", "HTML", "API"]
        },
        {
            "title": "Project 2",
            "desc": "it's exceptional, ",
            "img": "https://picsum.photos/200",
            "alt": "some alt text",
            "url": "https://github.com/zowie",
            "github": "https://github.com/jasonb2222",
            "skillset": ["CSS", "JS", "HTML", "NODE.JS"]
        },
        {
            "title": "Project 3",
            "desc": "it's knarly",
            "img": "https://picsum.photos/200",
            "alt": "some alt text",
            "url": "https://github.com/kapowie",
            "github": "https://github.com/jasonb2222",
            "skillset": ["CSS", "JS", "HTML", "TAILWIND"]
        },
    
}
